btcturk_api/__init__.py
btcturk_api/client.py
btcturk_api/constants.py
btcturk_api/exceptions.py
btcturk_api/properties.py
btcturk_api-1.8.1.dist-info/LICENSE.txt
btcturk_api-1.8.1.dist-info/METADATA
btcturk_api-1.8.1.dist-info/WHEEL
btcturk_api-1.8.1.dist-info/top_level.txt
btcturk_api-1.8.1.dist-info/RECORD
