Metadata-Version: 2.1
Name: btcturk-api
Version: 1.8.1
Summary: BTCTurk Rest API Python Implementation
Home-page: https://github.com/outlier-1/btcturkapi-python
Author: Ömer Miraç Baydemir
Author-email: omermirac59@gmail.com
License: UNKNOWN
Platform: UNKNOWN
Classifier: Programming Language :: Python :: 3
Classifier: Operating System :: OS Independent
Requires-Python: >=3.6
Requires-Dist: requests
